securegen/__init__.py
securegen/blue_team.py
securegen/cli.py
securegen/codegen.py
securegen/controller.py
securegen/models.py
securegen/red_team.py
securegen-0.2.0.dist-info/METADATA
securegen-0.2.0.dist-info/WHEEL
securegen-0.2.0.dist-info/entry_points.txt
securegen-0.2.0.dist-info/top_level.txt
securegen-0.2.0.dist-info/RECORD
