Metadata-Version: 2.4
Name: securegen
Version: 0.2.0
Summary: Multi-agent secure prompt CLI for AI code generation.
Requires-Python: >=3.10
Requires-Dist: openai>=1.40.0
Requires-Dist: anthropic>=0.34.0
